pydandy/__init__.py
pydandy/data.py
pydandy/database.py
pydandy/exceptions.py
pydandy/results.py
pydandy/table.py
pydandy/types.py
pydandy/utils.py
pydandy-0.0.1.dist-info/LICENSE
pydandy-0.0.1.dist-info/WHEEL
pydandy-0.0.1.dist-info/METADATA
pydandy-0.0.1.dist-info/RECORD
