Metadata-Version: 2.1
Name: pydandy
Version: 0.0.1
Summary: A handy-dandy datastore built on top of Pydantic
Home-page: https://github.com/WilliamJohns/pydandy
License: MIT
Author: Will Johns
Author-email: will@wcj.dev
Requires-Python: >=3.10,<4.0
Classifier: License :: OSI Approved :: MIT License
Classifier: Programming Language :: Python :: 3
Classifier: Programming Language :: Python :: 3.10
Requires-Dist: filelock (>=3.7.1,<4.0.0)
Requires-Dist: pydantic (>=1.9.1,<2.0.0)
Project-URL: Repository, https://github.com/WilliamJohns/pydandy
